privatize/__init__.py
privatize/core.py
privatize-0.0.1.dist-info/METADATA
privatize-0.0.1.dist-info/WHEEL
privatize-0.0.1.dist-info/top_level.txt
privatize-0.0.1.dist-info/zip-safe
privatize-0.0.1.dist-info/RECORD
