Metadata-Version: 2.1
Name: privatize
Version: 0.0.1
Summary: privatize
Home-page: https://www.lockhartlab.org
Author: C. Lockhart
Author-email: chris@lockhartlab.org
License: UNKNOWN
Platform: UNKNOWN
